app/__init__.py
app/main.py
app/sse.py
app/stdio.py
iflow_mcp_ragieai_fastapi_sse_mcp-0.1.0.dist-info/licenses/LICENSE
iflow_mcp_ragieai_fastapi_sse_mcp-0.1.0.dist-info/METADATA
iflow_mcp_ragieai_fastapi_sse_mcp-0.1.0.dist-info/WHEEL
iflow_mcp_ragieai_fastapi_sse_mcp-0.1.0.dist-info/entry_points.txt
iflow_mcp_ragieai_fastapi_sse_mcp-0.1.0.dist-info/top_level.txt
iflow_mcp_ragieai_fastapi_sse_mcp-0.1.0.dist-info/RECORD
