Metadata-Version: 2.4
Name: iflow-mcp_ragieai_fastapi-sse-mcp
Version: 0.1.0
Requires-Python: >=3.12
License-File: LICENSE
Requires-Dist: fastapi[standard]>=0.115.11
Requires-Dist: mcp>=1.4.1
Requires-Dist: ruff>=0.11.0
Dynamic: license-file
